chdb_core/__init__.py
chdb_core-0.0.1.dist-info/METADATA
chdb_core-0.0.1.dist-info/WHEEL
chdb_core-0.0.1.dist-info/top_level.txt
chdb_core-0.0.1.dist-info/RECORD
