Metadata-Version: 2.4
Name: chdb-core
Version: 0.0.1
Summary: Core library for chDB - an in-process SQL OLAP Engine powered by ClickHouse
Author-email: auxten <auxtenwpc@gmail.com>
Project-URL: Homepage, https://github.com/chdb-io/chdb
Project-URL: Issues, https://github.com/chdb-io/chdb/issues
Keywords: chdb,clickhouse,sql,olap,analytics
Classifier: Programming Language :: Python :: 3
Classifier: License :: OSI Approved :: Apache Software License
Classifier: Operating System :: OS Independent
Classifier: Development Status :: 1 - Planning
Requires-Python: >=3.8
